{
    "@schema": "https://raw.githubusercontent.com/slicer/slicer/master/Modules/Loadable/Markups/Resources/Schema/markups-schema-v1.0.3.json#",
    "markups": [
        {
            "type": "Fiducial",
            "coordinateSystem": "LPS",
            "coordinateUnits": "mm",
            "locked": false,
            "fixedNumberOfControlPoints": false,
            "labelFormat": "%N-%d",
            "lastUsedControlPointNumber": 6,
            "controlPoints": [
                {
                    "id": "1",
                    "label": "C",
                    "description": "",
                    "associatedNodeID": "vtkMRMLScalarVolumeNode5",
                    "position": [47.747486362432528, -18.433065692496347, -60.55063112411737],
                    "orientation": [-1.0, -0.0, -0.0, -0.0, -1.0, -0.0, 0.0, 0.0, 1.0],
                    "selected": true,
                    "locked": false,
                    "visibility": true,
                    "positionStatus": "defined"
                },
                {
                    "id": "2",
                    "label": "A",
                    "description": "",
                    "associatedNodeID": "vtkMRMLScalarVolumeNode5",
                    "position": [43.86176855224364, -18.68876636931274, -62.28757275889858],
                    "orientation": [-1.0, -0.0, -0.0, -0.0, -1.0, -0.0, 0.0, 0.0, 1.0],
                    "selected": true,
                    "locked": false,
                    "visibility": true,
                    "positionStatus": "defined"
                },
                {
                    "id": "3",
                    "label": "R",
                    "description": "",
                    "associatedNodeID": "vtkMRMLScalarVolumeNode5",
                    "position": [41.65268617306959, -17.257630737996679, -68.63803188552895],
                    "orientation": [-1.0, -0.0, -0.0, -0.0, -1.0, -0.0, 0.0, 0.0, 1.0],
                    "selected": true,
                    "locked": false,
                    "visibility": true,
                    "positionStatus": "defined"
                },
                {
                    "id": "4",
                    "label": "M",
                    "description": "",
                    "associatedNodeID": "vtkMRMLScalarVolumeNode5",
                    "position": [42.01914372734774, -16.368920658045697, -59.304728785483508],
                    "orientation": [-1.0, -0.0, -0.0, -0.0, -1.0, -0.0, 0.0, 0.0, 1.0],
                    "selected": true,
                    "locked": false,
                    "visibility": true,
                    "positionStatus": "defined"
                },
                {
                    "id": "5",
                    "label": "T",
                    "description": "",
                    "associatedNodeID": "vtkMRMLScalarVolumeNode5",
                    "position": [42.332730825077117, -17.481822785267526, -53.37823312626288],
                    "orientation": [-1.0, -0.0, -0.0, -0.0, -1.0, -0.0, 0.0, 0.0, 1.0],
                    "selected": true,
                    "locked": false,
                    "visibility": true,
                    "positionStatus": "defined"
                },
                {
                    "id": "6",
                    "label": "B",
                    "description": "",
                    "associatedNodeID": "vtkMRMLScalarVolumeNode5",
                    "position": [38.598722205698269, -24.66502274292413, -48.419941357710197],
                    "orientation": [-1.0, -0.0, -0.0, -0.0, -1.0, -0.0, 0.0, 0.0, 1.0],
                    "selected": true,
                    "locked": false,
                    "visibility": true,
                    "positionStatus": "defined"
                }
            ],
            "measurements": [],
            "display": {
                "visibility": false,
                "opacity": 1.0,
                "color": [0.4, 1.0, 0.0],
                "selectedColor": [1.0, 0.5000076295109484, 0.5000076295109484],
                "activeColor": [0.4, 1.0, 0.0],
                "propertiesLabelVisibility": false,
                "pointLabelsVisibility": true,
                "textScale": 3.0,
                "glyphType": "Sphere3D",
                "glyphScale": 1.0,
                "glyphSize": 5.0,
                "useGlyphScale": true,
                "sliceProjection": false,
                "sliceProjectionUseFiducialColor": true,
                "sliceProjectionOutlinedBehindSlicePlane": false,
                "sliceProjectionColor": [1.0, 1.0, 1.0],
                "sliceProjectionOpacity": 0.6,
                "lineThickness": 0.2,
                "lineColorFadingStart": 1.0,
                "lineColorFadingEnd": 10.0,
                "lineColorFadingSaturation": 1.0,
                "lineColorFadingHueOffset": 0.0,
                "handlesInteractive": false,
                "translationHandleVisibility": true,
                "rotationHandleVisibility": true,
                "scaleHandleVisibility": true,
                "interactionHandleScale": 3.0,
                "snapMode": "toVisibleSurface"
            }
        }
    ]
}